codefest/cf06/hdl/crossbar_mac.sv
`timescale 1ns / 1ps

module crossbar_mac (
    input  logic        clk,
    input  logic        rst_n,
    input  logic        enable,
    input  logic        weight_load,
    input  logic [3:0]  weight_row,
    input  logic [3:0]  weight_col,
    input  logic        weight_val,
    input  logic signed [7:0] in0,
    input  logic signed [7:0] in1,
    input  logic signed [7:0] in2,
    input  logic signed [7:0] in3,
    output logic signed [31:0] out0,
    output logic signed [31:0] out1,
    output logic signed [31:0] out2,
    output logic signed [31:0] out3
);

    // Weight matrix: 4x4 binary weights (+1/-1)
    // weight_matrix[i][j] = 0 represents +1, = 1 represents -1
    logic weight_matrix [0:3][0:3];

    // Input array for easier indexing
    logic signed [7:0] inputs [0:3];
    assign inputs[0] = in0;
    assign inputs[1] = in1;
    assign inputs[2] = in2;
    assign inputs[3] = in3;

    // Output accumulators
    logic signed [31:0] accumulators [0:3];
    assign out0 = accumulators[0];
    assign out1 = accumulators[1];
    assign out2 = accumulators[2];
    assign out3 = accumulators[3];

    // Intermediate products for each output
    logic signed [7:0] products [0:3][0:3];

    // Compute products: weight[i][j] * in[i]
    // If weight is 0 (+1): product = in[i]
    // If weight is 1 (-1): product = -in[i]
    // Unrolled for synthesis
    always_comb begin
        // Column 0
        products[0][0] = weight_matrix[0][0] ? -inputs[0] : inputs[0];
        products[1][0] = weight_matrix[1][0] ? -inputs[1] : inputs[1];
        products[2][0] = weight_matrix[2][0] ? -inputs[2] : inputs[2];
        products[3][0] = weight_matrix[3][0] ? -inputs[3] : inputs[3];

        // Column 1
        products[0][1] = weight_matrix[0][1] ? -inputs[0] : inputs[0];
        products[1][1] = weight_matrix[1][1] ? -inputs[1] : inputs[1];
        products[2][1] = weight_matrix[2][1] ? -inputs[2] : inputs[2];
        products[3][1] = weight_matrix[3][1] ? -inputs[3] : inputs[3];

        // Column 2
        products[0][2] = weight_matrix[0][2] ? -inputs[0] : inputs[0];
        products[1][2] = weight_matrix[1][2] ? -inputs[1] : inputs[1];
        products[2][2] = weight_matrix[2][2] ? -inputs[2] : inputs[2];
        products[3][2] = weight_matrix[3][2] ? -inputs[3] : inputs[3];

        // Column 3
        products[0][3] = weight_matrix[0][3] ? -inputs[0] : inputs[0];
        products[1][3] = weight_matrix[1][3] ? -inputs[1] : inputs[1];
        products[2][3] = weight_matrix[2][3] ? -inputs[2] : inputs[2];
        products[3][3] = weight_matrix[3][3] ? -inputs[3] : inputs[3];
    end

    // Weight loading logic
    always_ff @(posedge clk or negedge rst_n) begin
        if (!rst_n) begin
            // Initialize all weights to +1 (0)
            weight_matrix[0][0] <= 1'b0;
            weight_matrix[0][1] <= 1'b0;
            weight_matrix[0][2] <= 1'b0;
            weight_matrix[0][3] <= 1'b0;
            weight_matrix[1][0] <= 1'b0;
            weight_matrix[1][1] <= 1'b0;
            weight_matrix[1][2] <= 1'b0;
            weight_matrix[1][3] <= 1'b0;
            weight_matrix[2][0] <= 1'b0;
            weight_matrix[2][1] <= 1'b0;
            weight_matrix[2][2] <= 1'b0;
            weight_matrix[2][3] <= 1'b0;
            weight_matrix[3][0] <= 1'b0;
            weight_matrix[3][1] <= 1'b0;
            weight_matrix[3][2] <= 1'b0;
            weight_matrix[3][3] <= 1'b0;
        end else if (weight_load) begin
            // Load individual weight at (weight_row, weight_col)
            weight_matrix[weight_row][weight_col] <= weight_val;
        end
    end

    // MAC operation: out[j] = sum_i weight[i][j] * in[i]
    // Proper sign extension to 32-bit before addition
    always_ff @(posedge clk or negedge rst_n) begin
        if (!rst_n) begin
            accumulators[0] <= 32'sd0;
            accumulators[1] <= 32'sd0;
            accumulators[2] <= 32'sd0;
            accumulators[3] <= 32'sd0;
        end else if (enable) begin
            // Sign-extend first operand to 32-bit, rest will follow
            accumulators[0] <= $signed({{24{products[0][0][7]}}, products[0][0]}) +
                              $signed({{24{products[1][0][7]}}, products[1][0]}) +
                              $signed({{24{products[2][0][7]}}, products[2][0]}) +
                              $signed({{24{products[3][0][7]}}, products[3][0]});

            accumulators[1] <= $signed({{24{products[0][1][7]}}, products[0][1]}) +
                              $signed({{24{products[1][1][7]}}, products[1][1]}) +
                              $signed({{24{products[2][1][7]}}, products[2][1]}) +
                              $signed({{24{products[3][1][7]}}, products[3][1]});

            accumulators[2] <= $signed({{24{products[0][2][7]}}, products[0][2]}) +
                              $signed({{24{products[1][2][7]}}, products[1][2]}) +
                              $signed({{24{products[2][2][7]}}, products[2][2]}) +
                              $signed({{24{products[3][2][7]}}, products[3][2]});

            accumulators[3] <= $signed({{24{products[0][3][7]}}, products[0][3]}) +
                              $signed({{24{products[1][3][7]}}, products[1][3]}) +
                              $signed({{24{products[2][3][7]}}, products[2][3]}) +
                              $signed({{24{products[3][3][7]}}, products[3][3]});
        end
    end

endmodule

codefest/cf06/hdl/crossbar_tb.sv
`timescale 1ns / 1ps

module crossbar_tb;

    // Clock and reset
    logic clk;
    logic rst_n;

    // Control signals
    logic enable;
    logic weight_load;
    logic [3:0] weight_row;
    logic [3:0] weight_col;
    logic weight_val;

    // Data signals
    logic signed [7:0] in0, in1, in2, in3;
    logic signed [31:0] out0, out1, out2, out3;

    // Instantiate DUT
    crossbar_mac dut (
        .clk(clk),
        .rst_n(rst_n),
        .enable(enable),
        .weight_load(weight_load),
        .weight_row(weight_row),
        .weight_col(weight_col),
        .weight_val(weight_val),
        .in0(in0),
        .in1(in1),
        .in2(in2),
        .in3(in3),
        .out0(out0),
        .out1(out1),
        .out2(out2),
        .out3(out3)
    );

    // Clock generation: 10ns period (100MHz)
    initial begin
        clk = 0;
        forever #5 clk = ~clk;
    end

    // Test stimulus
    initial begin
        // Initialize signals
        rst_n = 0;
        enable = 0;
        weight_load = 0;
        weight_row = 0;
        weight_col = 0;
        weight_val = 0;
        in0 = 0;
        in1 = 0;
        in2 = 0;
        in3 = 0;

        // Wait for a few cycles
        repeat(3) @(posedge clk);

        // Release reset
        rst_n = 1;
        @(posedge clk);

        $display("=== Crossbar MAC Testbench ===");
        $display("Loading weight matrix:");
        $display("  [[ 1, -1,  1, -1],");
        $display("   [ 1,  1, -1, -1],");
        $display("   [-1,  1,  1, -1],");
        $display("   [-1, -1, -1,  1]]");
        $display("");

        // Load weights
        // Weight encoding: 0 = +1, 1 = -1
        // Row 0: [1, -1, 1, -1] -> [0, 1, 0, 1]
        load_weight(0, 0, 0); // +1
        load_weight(0, 1, 1); // -1
        load_weight(0, 2, 0); // +1
        load_weight(0, 3, 1); // -1

        // Row 1: [1, 1, -1, -1] -> [0, 0, 1, 1]
        load_weight(1, 0, 0); // +1
        load_weight(1, 1, 0); // +1
        load_weight(1, 2, 1); // -1
        load_weight(1, 3, 1); // -1

        // Row 2: [-1, 1, 1, -1] -> [1, 0, 0, 1]
        load_weight(2, 0, 1); // -1
        load_weight(2, 1, 0); // +1
        load_weight(2, 2, 0); // +1
        load_weight(2, 3, 1); // -1

        // Row 3: [-1, -1, -1, 1] -> [1, 1, 1, 0]
        load_weight(3, 0, 1); // -1
        load_weight(3, 1, 1); // -1
        load_weight(3, 2, 1); // -1
        load_weight(3, 3, 0); // +1

        $display("Weights loaded successfully");
        $display("");

        // Apply inputs [10, 20, 30, 40]
        $display("Applying inputs: [10, 20, 30, 40]");
        @(posedge clk);
        in0 = 8'sd10;
        in1 = 8'sd20;
        in2 = 8'sd30;
        in3 = 8'sd40;
        enable = 1;

        // Wait for computation
        @(posedge clk);
        @(posedge clk);

        // Check results
        $display("");
        $display("=== Results ===");
        $display("Expected outputs:");
        $display("  out[0] = (1*10) + (1*20) + (-1*30) + (-1*40) = 10 + 20 - 30 - 40 = -40");
        $display("  out[1] = (-1*10) + (1*20) + (1*30) + (-1*40) = -10 + 20 + 30 - 40 = 0");
        $display("  out[2] = (1*10) + (-1*20) + (1*30) + (-1*40) = 10 - 20 + 30 - 40 = -20");
        $display("  out[3] = (-1*10) + (-1*20) + (-1*30) + (1*40) = -10 - 20 - 30 + 40 = -20");
        $display("");
        $display("Actual outputs:");
        $display("  out[0] = %0d %s", out0, (out0 == -40) ? "✓" : "✗ FAIL");
        $display("  out[1] = %0d %s", out1, (out1 == 0) ? "✓" : "✗ FAIL");
        $display("  out[2] = %0d %s", out2, (out2 == -20) ? "✓" : "✗ FAIL");
        $display("  out[3] = %0d %s", out3, (out3 == -20) ? "✓" : "✗ FAIL");
        $display("");

        // Verify results
        if (out0 == -40 && out1 == 0 && out2 == -20 && out3 == -20) begin
            $display("=== TEST PASSED ===");
        end else begin
            $display("=== TEST FAILED ===");
            $display("Mismatch detected!");
        end

        // Run a few more cycles
        repeat(5) @(posedge clk);

        $finish;
    end

    // Task to load a single weight
    task load_weight(input [3:0] row, input [3:0] col, input val);
        begin
            @(posedge clk);
            weight_load = 1;
            weight_row = row;
            weight_col = col;
            weight_val = val;
            @(posedge clk);
            weight_load = 0;
        end
    endtask

    // Optional: VCD dump for waveform viewing
    initial begin
        $dumpfile("crossbar_tb.vcd");
        $dumpvars(0, crossbar_tb);
    end

endmodule

codefest/cf06/hdl/crossbar_tb.vcd
$date
	Wed May  6 17:13:47 2026
$end
$version
	Icarus Verilog
$end
$timescale
	1ps
$end
$scope module crossbar_tb $end
$var wire 32 ! out3 [31:0] $end
$var wire 32 " out2 [31:0] $end
$var wire 32 # out1 [31:0] $end
$var wire 32 $ out0 [31:0] $end
$var reg 1 % clk $end
$var reg 1 & enable $end
$var reg 8 ' in0 [7:0] $end
$var reg 8 ( in1 [7:0] $end
$var reg 8 ) in2 [7:0] $end
$var reg 8 * in3 [7:0] $end
$var reg 1 + rst_n $end
$var reg 4 , weight_col [3:0] $end
$var reg 1 - weight_load $end
$var reg 4 . weight_row [3:0] $end
$var reg 1 / weight_val $end
$scope module dut $end
$var wire 1 % clk $end
$var wire 1 & enable $end
$var wire 8 0 in0 [7:0] $end
$var wire 8 1 in1 [7:0] $end
$var wire 8 2 in2 [7:0] $end
$var wire 8 3 in3 [7:0] $end
$var wire 32 4 out0 [31:0] $end
$var wire 32 5 out1 [31:0] $end
$var wire 32 6 out2 [31:0] $end
$var wire 32 7 out3 [31:0] $end
$var wire 1 + rst_n $end
$var wire 4 8 weight_col [3:0] $end
$var wire 1 - weight_load $end
$var wire 4 9 weight_row [3:0] $end
$var wire 1 / weight_val $end
$upscope $end
$scope task load_weight $end
$var reg 4 : col [3:0] $end
$var reg 4 ; row [3:0] $end
$var reg 1 < val $end
$upscope $end
$upscope $end
$enddefinitions $end
$comment Show the parameter values. $end
$dumpall
$end
#0
$dumpvars
x<
bx ;
bx :
b0 9
b0 8
b0 7
b0 6
b0 5
b0 4
b0 3
b0 2
b0 1
b0 0
0/
b0 .
0-
b0 ,
0+
b0 *
b0 )
b0 (
b0 '
0&
0%
b0 $
b0 #
b0 "
b0 !
$end
#5000
1%
#10000
0%
#15000
1%
#20000
0%
#25000
1+
1%
#30000
0%
#35000
0<
b0 :
b0 ;
1%
#40000
0%
#45000
1-
1%
#50000
0%
#55000
1<
b1 :
0-
1%
#60000
0%
#65000
1/
b1 ,
b1 8
1-
1%
#70000
0%
#75000
0<
b10 :
0-
1%
#80000
0%
#85000
0/
b10 ,
b10 8
1-
1%
#90000
0%
#95000
1<
b11 :
0-
1%
#100000
0%
#105000
1/
b11 ,
b11 8
1-
1%
#110000
0%
#115000
0<
b0 :
b1 ;
0-
1%
#120000
0%
#125000
0/
b0 ,
b0 8
b1 .
b1 9
1-
1%
#130000
0%
#135000
b1 :
0-
1%
#140000
0%
#145000
b1 ,
b1 8
1-
1%
#150000
0%
#155000
1<
b10 :
0-
1%
#160000
0%
#165000
1/
b10 ,
b10 8
1-
1%
#170000
0%
#175000
b11 :
0-
1%
#180000
0%
#185000
b11 ,
b11 8
1-
1%
#190000
0%
#195000
b0 :
b10 ;
0-
1%
#200000
0%
#205000
b0 ,
b0 8
b10 .
b10 9
1-
1%
#210000
0%
#215000
0<
b1 :
0-
1%
#220000
0%
#225000
0/
b1 ,
b1 8
1-
1%
#230000
0%
#235000
b10 :
0-
1%
#240000
0%
#245000
b10 ,
b10 8
1-
1%
#250000
0%
#255000
1<
b11 :
0-
1%
#260000
0%
#265000
1/
b11 ,
b11 8
1-
1%
#270000
0%
#275000
b0 :
b11 ;
0-
1%
#280000
0%
#285000
b0 ,
b0 8
b11 .
b11 9
1-
1%
#290000
0%
#295000
b1 :
0-
1%
#300000
0%
#305000
b1 ,
b1 8
1-
1%
#310000
0%
#315000
b10 :
0-
1%
#320000
0%
#325000
b10 ,
b10 8
1-
1%
#330000
0%
#335000
0<
b11 :
0-
1%
#340000
0%
#345000
0/
b11 ,
b11 8
1-
1%
#350000
0%
#355000
0-
1%
#360000
0%
#365000
1&
b101000 *
b101000 3
b11110 )
b11110 2
b10100 (
b10100 1
b1010 '
b1010 0
1%
#370000
0%
#375000
b11111111111111111111111111101100 !
b11111111111111111111111111101100 7
b11111111111111111111111111101100 "
b11111111111111111111111111101100 6
b11111111111111111111111111011000 $
b11111111111111111111111111011000 4
1%
